pyuartsi/__init__.py
pyuartsi/__main__.py
pyuartsi/uart_tsi.py
pyuartsi/csrc/Makefile
pyuartsi/csrc/serial.c
pyuartsi-2026.1.20.dist-info/METADATA
pyuartsi-2026.1.20.dist-info/WHEEL
pyuartsi-2026.1.20.dist-info/licenses/LICENSE
pyuartsi-2026.1.20.dist-info/RECORD
