Metadata-Version: 2.4
Name: pyuartsi
Version: 2026.1.20
Summary: A standalone implementation of the Tethered Serial Interface (TSI) in Python.
Project-URL: Homepage, https://github.com/ucb-bar/pyuartsi
Author-email: "-T.K.-" <t_k_233@outlook.email>
License: MIT License
License-File: LICENSE
Classifier: License :: OSI Approved :: MIT License
Classifier: Operating System :: OS Independent
Classifier: Programming Language :: Python :: 3
Requires-Python: >=3.10
Requires-Dist: pyelftools
Requires-Dist: pyserial
Requires-Dist: rich
